brunner_pg/__init__.py
brunner_pg/client.py
brunner_pg/py.typed
brunner_pg-1.8.0.dist-info/METADATA
brunner_pg-1.8.0.dist-info/WHEEL
brunner_pg-1.8.0.dist-info/RECORD
